Metadata-Version: 1.0
Name: rask-njord-mercadolivre
Version: 0.0.2
Summary: Rask Mercadolivre Connector
Home-page: https://gitlab.com/vikingmakt/rask_njord_mercadolivre
Author: Umgeher Torgersen
Author-email: me@umgeher.org
License: https://gitlab.com/vikingmakt/rask_njord_mercadolivre/raw/master/LICENSE
Platform: UNKNOWN
